cwaft/algorithms/__init__.py
cwaft/algorithms/kmeans.py
cwaft-0.1.2.dist-info/WHEEL
cwaft-0.1.2.dist-info/METADATA
cwaft-0.1.2.dist-info/RECORD
