Metadata-Version: 2.1
Name: cwaft
Version: 0.1.2
Summary: A Python library of mathematical tools and algorithms.
Home-page: https://github.com/brentnequin/cwaft
License: MIT
Author: brentnequin
Author-email: brentnequin@gmail.com
Requires-Python: >=3.9,<4.0
Classifier: License :: OSI Approved :: MIT License
Classifier: Programming Language :: Python :: 3
Classifier: Programming Language :: Python :: 3.9
Classifier: Programming Language :: Python :: 3.10
Classifier: Programming Language :: Python :: 3.11
Requires-Dist: numpy (>=1.24.1,<2.0.0)
Project-URL: Repository, https://github.com/brentnequin/cwaft
